08_mux/mux2to1.sv
module mux2to1(
    input logic A,
    input logic B,
    input logic S,
    output logic Y
);

assign Y = (~S & A) | (S & B);

endmodule

08_mux/tb_mux2to1.sv
module tb_mux2to1;

logic A;
logic B;
logic S;
logic Y;

mux2to1 uut (
    .A(A),
    .B(B),
    .S(S),
    .Y(Y)
);

initial begin

    $dumpfile("mux2to1.vcd");
    $dumpvars(0, tb_mux2to1);

    A = 0; B = 0; S = 0;
    #10;

    A = 0; B = 1; S = 0;
    #10;

    A = 1; B = 0; S = 0;
    #10;

    A = 1; B = 1; S = 0;
    #10;

    A = 0; B = 0; S = 1;
    #10;

    A = 0; B = 1; S = 1;
    #10;

    A = 1; B = 0; S = 1;
    #10;

    A = 1; B = 1; S = 1;
    #10;

    $finish;

end

always #5 $display("Time=%0t A=%b B=%b S=%b Y=%b", $time, A, B, S, Y);

endmodule

08_mux/mux2to1.vcd
$date
	Thu Oct  8 04:12:47 2026
$end
$version
	Icarus Verilog
$end
$timescale
	1s
$end
$scope module tb_mux2to1 $end
$var wire 1 ! Y $end
$var reg 1 " A $end
$var reg 1 # B $end
$var reg 1 $ S $end
$scope module uut $end
$var wire 1 " A $end
$var wire 1 # B $end
$var wire 1 $ S $end
$var wire 1 ! Y $end
$upscope $end
$upscope $end
$enddefinitions $end
$comment Show the parameter values. $end
$dumpall
$end
#0
$dumpvars
0$
0#
0"
0!
$end
#10
1#
#20
1!
0#
1"
#30
1#
#40
0!
1$
0#
0"
#50
1!
1#
#60
0!
0#
1"
#70
1!
1#
